[
    {
        "id": "debate-001",
        "category": "FICTIONAL DEBATE",
        "debater1": {
            "name": "HIROO",
            "photo": "img/IMG_0524.jpeg",
            "country": "indonesia",
            "flag": "img/IMG_0417.png"
        },
        "debater2": {
            "name": "RENJI",
            "photo": "img/IMG_0523.jpeg",
            "country": "malaysia",
            "flag": "img/IMG_0418.png"
        },
        "type": "ONE-ON-ONE DEBATE",
        "winner": {
            "name": "HIROO",
            "method": "limit"
        },
        "loser": {
            "name": "RENJI"
        }
    },
    {
        "id": "debate-002",
        "category": "FICTIONAL DEBATE",
        "debater1": {
            "name": "ZOGRATIS",
            "photo": "img/IMG_0526.jpeg",
            "country": "indonesia",
            "flag": "img/IMG_0417.png"
        },
        "debater2": {
            "name": "MUCHIBEI",
            "photo": "img/IMG_0530.jpeg",
            "country": "malaysia",
            "flag": "img/IMG_0418.png"
        },
        "type": "ONE-ON-ONE DEBATE",
        "winner": {
            "name": "ZOGRATIS",
            "method": "point"
        },
        "loser": {
            "name": "MUCHIBEI"
        }
    },
    {
        "id": "debate-003",
        "category": "FICTIONAL DEBATE",
        "debater1": {
            "name": "ARYANWT",
            "photo": "img/IMG_0525.jpeg",
            "country": "indonesia",
            "flag": "img/IMG_0417.png"
        },
        "debater2": {
            "name": "RIM",
            "photo": "img/IMG_0527.jpeg",
            "country": "malaysia",
            "flag": "img/IMG_0418.png"
        },
        "type": "ONE-ON-ONE DEBATE",
        "winner": {
            "name": "ARYANWT",
            "method": "point"
        },
        "loser": {
            "name": "RIM"
        }
    },
    {
        "id": "debate-004",
        "category": "FICTIONAL DEBATE",
        "debater1": {
            "name": "RANZT",
            "photo": "img/ranzt.jpg",  "country": "indonesia",
            "flag": "img/IMG_0417.png"
        },
        "debater2": {
            "name": "RYUU",
            "photo": "img/ryuu.jpg",  "country": "malaysia",
            "flag": "img/IMG_0418.png"
        },
        "type": "ONE-ON-ONE DEBATE",
        "winner": {
            "name": "RANZT",
            "method": "point"
        },
        "loser": {
            "name": "RYUU"
        }
    }
]
